{"action_pressed":{"Category":"Character","Input_Action":"action","Key1":"32","Key2":"16777238"},"jump":{"Category":"Character","Input_Action":"Jump","Key1":"74","Key2":"16777240","KeySelect_Template":"","KeySelect_Template2":""},"move_down":{"Category":"Character","Input_Action":"Down","Key1":83,"Key2":16777234},"move_left":{"Category":"Character","Input_Action":"Move Left","Key1":"65","Key2":"16777231"},"move_right":{"Category":"Character","Input_Action":"Move Right","Key1":"68","Key2":"16777233","KeySelect_Template":"","KeySelect_Template2":""},"move_up":{"Category":"Character","Input_Action":"Up","Key1":87,"Key2":16777232}}
